LICENSE.txt
README.md
setup.cfg
setup.py
meili_sdk/__init__.py
meili_sdk/exceptions.py
meili_sdk/site.py
meili_sdk/token.py
meili_sdk/utils.py
meili_sdk/version.py
meili_sdk.egg-info/PKG-INFO
meili_sdk.egg-info/SOURCES.txt
meili_sdk.egg-info/dependency_links.txt
meili_sdk.egg-info/requires.txt
meili_sdk.egg-info/top_level.txt
meili_sdk/clients/__init__.py
meili_sdk/clients/apitoken_client.py
meili_sdk/clients/base.py
meili_sdk/clients/persistent_token_client.py
meili_sdk/clients/sdk_client.py
meili_sdk/config/__init__.py
meili_sdk/config/type.py
meili_sdk/config/utils.py
meili_sdk/models/__init__.py
meili_sdk/models/base.py
meili_sdk/models/form.py
meili_sdk/models/organization.py
meili_sdk/models/ros_setup.py
meili_sdk/models/task.py
meili_sdk/models/team.py
meili_sdk/models/trigger.py
meili_sdk/models/user.py
meili_sdk/models/vehicle.py
meili_sdk/mqtt/__init__.py
meili_sdk/mqtt/action_client.py
meili_sdk/mqtt/client.py
meili_sdk/mqtt/site.py
meili_sdk/mqtt/models/__init__.py
meili_sdk/mqtt/models/action.py
meili_sdk/mqtt/models/connection.py
meili_sdk/mqtt/models/factsheet.py
meili_sdk/mqtt/models/order.py
meili_sdk/mqtt/models/state.py
meili_sdk/resources/__init__.py
meili_sdk/resources/base.py
meili_sdk/resources/forms.py
meili_sdk/resources/maps.py
meili_sdk/resources/organizations.py
meili_sdk/resources/ros.py
meili_sdk/resources/tasks.py
meili_sdk/resources/teams.py
meili_sdk/resources/triggers.py
meili_sdk/resources/users.py
meili_sdk/resources/vehicles.py
meili_sdk/schedules/__init__.py
meili_sdk/schedules/exceptions.py
meili_sdk/schedules/loader.py
meili_sdk/schedules/models.py
meili_sdk/websockets/__init__.py
meili_sdk/websockets/client.py
meili_sdk/websockets/constants.py
meili_sdk/websockets/models/__init__.py
meili_sdk/websockets/models/action_definition.py
meili_sdk/websockets/models/cancel_task_message.py
meili_sdk/websockets/models/docking_routine_message.py
meili_sdk/websockets/models/message.py
meili_sdk/websockets/models/move_message.py
meili_sdk/websockets/models/path.py
meili_sdk/websockets/models/preset.py
meili_sdk/websockets/models/station.py
meili_sdk/websockets/models/task.py
