Metadata-Version: 2.1
Name: meili-sdk
Version: 0.8.7
Summary: Meili FMS SDK
Home-page: https://gitlab.com/meilirobots/dev/meili-sdk
Author: Meili Robots
Author-email: info@meilirobots.com
License: MIT
Provides-Extra: MQTT
License-File: LICENSE.txt
